odoo8_addon_partner_contact_nationality-8.0.1.0.0.99.dev8-py2.7-nspkg.pth
odoo8_addon_partner_contact_nationality-8.0.1.0.0.99.dev8.dist-info/METADATA
odoo8_addon_partner_contact_nationality-8.0.1.0.0.99.dev8.dist-info/RECORD
odoo8_addon_partner_contact_nationality-8.0.1.0.0.99.dev8.dist-info/WHEEL
odoo8_addon_partner_contact_nationality-8.0.1.0.0.99.dev8.dist-info/namespace_packages.txt
odoo8_addon_partner_contact_nationality-8.0.1.0.0.99.dev8.dist-info/top_level.txt
odoo_addons/partner_contact_nationality/README.rst
odoo_addons/partner_contact_nationality/__init__.py
odoo_addons/partner_contact_nationality/__openerp__.py
odoo_addons/partner_contact_nationality/models.py
odoo_addons/partner_contact_nationality/i18n/de.po
odoo_addons/partner_contact_nationality/i18n/es.po
odoo_addons/partner_contact_nationality/i18n/eu.po
odoo_addons/partner_contact_nationality/i18n/fi.po
odoo_addons/partner_contact_nationality/i18n/fr.po
odoo_addons/partner_contact_nationality/i18n/it.po
odoo_addons/partner_contact_nationality/i18n/nl.po
odoo_addons/partner_contact_nationality/i18n/partner_contact_nationality.pot
odoo_addons/partner_contact_nationality/i18n/sl.po
odoo_addons/partner_contact_nationality/static/description/icon.png
odoo_addons/partner_contact_nationality/views/res_partner.xml
